conventions/__init__.py
conventions/__main__.py
conventions/cache.py
conventions/cli.py
conventions/config.py
conventions/fs.py
conventions/plugins.py
conventions/ratings.py
conventions/report.py
conventions/scan.py
conventions/schemas.py
conventions/detectors/__init__.py
conventions/detectors/base.py
conventions/detectors/orchestrator.py
conventions/detectors/registry.py
conventions/detectors/generic/__init__.py
conventions/detectors/generic/api_docs.py
conventions/detectors/generic/ci_cd.py
conventions/detectors/generic/containerization.py
conventions/detectors/generic/dependency_updates.py
conventions/detectors/generic/editor_config.py
conventions/detectors/generic/git_conventions.py
conventions/detectors/generic/repo_layout.py
conventions/detectors/go/__init__.py
conventions/detectors/go/api.py
conventions/detectors/go/architecture.py
conventions/detectors/go/base.py
conventions/detectors/go/cli.py
conventions/detectors/go/codegen.py
conventions/detectors/go/concurrency.py
conventions/detectors/go/conventions.py
conventions/detectors/go/di.py
conventions/detectors/go/documentation.py
conventions/detectors/go/errors.py
conventions/detectors/go/grpc.py
conventions/detectors/go/index.py
conventions/detectors/go/logging.py
conventions/detectors/go/migrations.py
conventions/detectors/go/modules.py
conventions/detectors/go/patterns.py
conventions/detectors/go/security.py
conventions/detectors/go/testing.py
conventions/detectors/node/__init__.py
conventions/detectors/node/api.py
conventions/detectors/node/architecture.py
conventions/detectors/node/async_patterns.py
conventions/detectors/node/base.py
conventions/detectors/node/build_tools.py
conventions/detectors/node/conventions.py
conventions/detectors/node/documentation.py
conventions/detectors/node/errors.py
conventions/detectors/node/formatting.py
conventions/detectors/node/frontend.py
conventions/detectors/node/index.py
conventions/detectors/node/linting.py
conventions/detectors/node/logging.py
conventions_cli-1.0.0.dist-info/licenses/LICENSE
conventions_cli-1.0.0.dist-info/METADATA
conventions_cli-1.0.0.dist-info/WHEEL
conventions_cli-1.0.0.dist-info/entry_points.txt
conventions_cli-1.0.0.dist-info/top_level.txt
conventions_cli-1.0.0.dist-info/RECORD
