Metadata-Version: 2.4
Name: conventions-cli
Version: 1.0.0
Summary: Automatically discover and document coding conventions in your codebase
Author: Stephanie Dover
License: MIT
Project-URL: Homepage, https://github.com/steph-dove/conventions
Project-URL: Repository, https://github.com/steph-dove/conventions
Project-URL: Issues, https://github.com/steph-dove/conventions/issues
Keywords: conventions,code-analysis,static-analysis,code-quality,best-practices,linting,python,typescript,golang,rust
Classifier: Development Status :: 4 - Beta
Classifier: Intended Audience :: Developers
Classifier: License :: OSI Approved :: MIT License
Classifier: Operating System :: OS Independent
Classifier: Programming Language :: Python :: 3
Classifier: Programming Language :: Python :: 3.10
Classifier: Programming Language :: Python :: 3.11
Classifier: Programming Language :: Python :: 3.12
Classifier: Programming Language :: Python :: 3.13
Classifier: Topic :: Software Development :: Quality Assurance
Classifier: Topic :: Software Development :: Testing
Classifier: Typing :: Typed
Requires-Python: >=3.10
License-File: LICENSE
Requires-Dist: typer>=0.9.0
Requires-Dist: rich>=13.0.0
Requires-Dist: pydantic>=2.0.0
Requires-Dist: pathspec>=0.11.0
Provides-Extra: dev
Requires-Dist: pytest>=7.0.0; extra == "dev"
Requires-Dist: pytest-cov>=4.0.0; extra == "dev"
Requires-Dist: pytest-asyncio>=0.21.0; extra == "dev"
Requires-Dist: mypy>=1.0.0; extra == "dev"
Requires-Dist: ruff>=0.1.0; extra == "dev"
Dynamic: license-file
